spot_planner-0.3.6.dist-info/METADATA
spot_planner-0.3.6.dist-info/WHEEL
spot_planner/__init__.py
spot_planner/brute_force.py
spot_planner/main.py
spot_planner/py.typed
spot_planner/spot_planner.cpython-311-x86_64-linux-gnu.so
spot_planner/two_phase.py
spot_planner-0.3.6.dist-info/RECORD
