Metadata-Version: 2.4
Name: spot-planner
Version: 0.3.6
Classifier: Development Status :: 4 - Beta
Classifier: Intended Audience :: Developers
Classifier: Intended Audience :: Science/Research
Classifier: License :: OSI Approved :: MIT License
Classifier: Operating System :: OS Independent
Classifier: Programming Language :: Python :: 3
Classifier: Programming Language :: Python :: 3.10
Classifier: Programming Language :: Python :: 3.11
Classifier: Programming Language :: Python :: 3.12
Classifier: Programming Language :: Python :: 3.13
Classifier: Programming Language :: Python :: 3.14
Classifier: Programming Language :: Rust
Classifier: Topic :: Scientific/Engineering :: Mathematics
Classifier: Topic :: Software Development :: Libraries :: Python Modules
Classifier: Typing :: Typed
Requires-Dist: matplotlib>=3.10.7
Requires-Dist: numpy>=2.2.6
Summary: Algorithm for finding the cheapest periods in a sequence of prices
Keywords: spot-pricing,optimization,algorithm,cost-analysis,time-series
Author-email: Jaakko Vuori <jaakko.vuori@gmail.com>
License: MIT
Requires-Python: >=3.10
Project-URL: Homepage, https://github.com/jvuori/spot-planner
Project-URL: Bug Reports, https://github.com/jvuori/spot-planner/issues
Project-URL: Source, https://github.com/jvuori/spot-planner
Project-URL: Documentation, https://github.com/jvuori/spot-planner#readme
